github_research_mcp/__init__.py
github_research_mcp/agents_md.py
github_research_mcp/clients/__init__.py
github_research_mcp/clients/cache.py
github_research_mcp/clients/elasticsearch.py
github_research_mcp/clients/errors/github.py
github_research_mcp/clients/github.py
github_research_mcp/clients/models/github.py
github_research_mcp/code_search.py
github_research_mcp/main.py
github_research_mcp/models/__init__.py
github_research_mcp/models/graphql/__init__.py
github_research_mcp/models/graphql/base.py
github_research_mcp/models/graphql/fragments.py
github_research_mcp/models/graphql/issue_or_pull_request.py
github_research_mcp/models/repository/tree.py
github_research_mcp/models/rest/models.py
github_research_mcp/sampling/extract.py
github_research_mcp/sampling/handler.py
github_research_mcp/sampling/utility.py
github_research_mcp/servers/code.py
github_research_mcp/servers/prompts/summarize_repository.py
github_research_mcp/servers/research.py
github_research_mcp/servers/shared/annotations.py
github_research_mcp/servers/shared/errors.py
github_research_mcp/servers/shared/prompts.py
github_research_mcp/servers/summary.py
github_research_mcp/utilities/stars.py
github_research_mcp/vendored/caching.py
github_research_mcp/vendored/elasticsearch_cache.py
github_research_mcp/vendored/google_genai.py
github_research_mcp-0.2.0.dist-info/WHEEL
github_research_mcp-0.2.0.dist-info/entry_points.txt
github_research_mcp-0.2.0.dist-info/METADATA
github_research_mcp-0.2.0.dist-info/RECORD
