Metadata-Version: 2.3
Name: github-research-mcp
Version: 0.2.0
Summary: Github Research MCP project
Requires-Dist: aiohttp>=3.12.15
Requires-Dist: click>=8.3.0
Requires-Dist: diskcache>=5.6.3
Requires-Dist: elasticsearch>=9.1.1
Requires-Dist: fastmcp>=2.3.5
Requires-Dist: githubkit>=0.13.2
Requires-Dist: gitpython>=3.1.45
Requires-Dist: google-genai>=1.37.0
Requires-Dist: makefun>=1.16.0
Requires-Dist: mcp>=1.9.0
Requires-Dist: openai>=1.106.1
Requires-Dist: pydantic>=2.11.7
Requires-Dist: rpygrep>=0.2.0
Requires-Python: >=3.12
